auto_package_framework-0.2.3.dist-info/licenses/LICENSE
framework/__init__.py
framework/ai_developer.py
framework/cli.py
framework/code_generator.py
framework/config.py
framework/config_manager.py
framework/core.py
framework/github_client.py
framework/project_generator.py
framework/pypi_client.py
framework/skill.py
framework/templates/.gitignore
framework/templates/.pre-commit-config.yaml
framework/templates/AI_CONTEXT.md
framework/templates/AI_START_PROMPT.md
framework/templates/CHANGELOG.md
framework/templates/CODE_OF_CONDUCT.md
framework/templates/CONTRIBUTING.md
framework/templates/LICENSE
framework/templates/Makefile
framework/templates/PROJECT_IDEA.md
framework/templates/QUICK_START.md
framework/templates/README.md
framework/templates/README_TEMPLATE.md
framework/templates/SECURITY.md
framework/templates/START_HERE.md
framework/templates/__init__.py
framework/templates/cookiecutter.json
framework/templates/llms.txt.template
framework/templates/pyproject.toml
framework/templates/release-please-config.json
framework/templates/.github/dependabot.yml
framework/templates/.github/pull_request_template.md
framework/templates/.github/ISSUE_TEMPLATE/bug_report.yml
framework/templates/.github/ISSUE_TEMPLATE/feature_request.yml
framework/templates/.github/workflows/ci.yml
framework/templates/.github/workflows/release.yml
framework/templates/{{ cookiecutter.project_name }}/.gitignore
framework/templates/{{ cookiecutter.project_name }}/.pre-commit-config.yaml
framework/templates/{{ cookiecutter.project_name }}/AI_CONTEXT.md
framework/templates/{{ cookiecutter.project_name }}/AI_START_PROMPT.md
framework/templates/{{ cookiecutter.project_name }}/CHANGELOG.md
framework/templates/{{ cookiecutter.project_name }}/CODE_OF_CONDUCT.md
framework/templates/{{ cookiecutter.project_name }}/CONTRIBUTING.md
framework/templates/{{ cookiecutter.project_name }}/LICENSE
framework/templates/{{ cookiecutter.project_name }}/Makefile
framework/templates/{{ cookiecutter.project_name }}/PROJECT_IDEA.md
auto_package_framework-0.2.3.dist-info/METADATA
auto_package_framework-0.2.3.dist-info/WHEEL
auto_package_framework-0.2.3.dist-info/entry_points.txt
auto_package_framework-0.2.3.dist-info/top_level.txt
auto_package_framework-0.2.3.dist-info/RECORD
