Metadata-Version: 2.4
Name: auto-package-framework
Version: 0.2.3
Summary: AI驱动的自动化Python包创建、开发和发布框架
Author-email: Auto Project <auto@example.com>
License: MIT
Project-URL: Homepage, https://github.com/flashpoint493/auto-package-framework
Project-URL: Documentation, https://github.com/flashpoint493/auto-package-framework#readme
Project-URL: Repository, https://github.com/flashpoint493/auto-package-framework
Project-URL: Issues, https://github.com/flashpoint493/auto-package-framework/issues
Keywords: automation,ai,package,github,pypi
Classifier: Development Status :: 3 - Alpha
Classifier: Intended Audience :: Developers
Classifier: License :: OSI Approved :: MIT License
Classifier: Programming Language :: Python :: 3
Classifier: Programming Language :: Python :: 3.8
Classifier: Programming Language :: Python :: 3.9
Classifier: Programming Language :: Python :: 3.10
Classifier: Programming Language :: Python :: 3.11
Classifier: Programming Language :: Python :: 3.12
Requires-Python: >=3.8
License-File: LICENSE
Requires-Dist: PyGithub>=2.0.0
Requires-Dist: GitPython>=3.1.40
Requires-Dist: pyyaml>=6.0
Requires-Dist: jinja2>=3.1.2
Requires-Dist: click>=8.1.7
Requires-Dist: openai>=1.0.0
Requires-Dist: anthropic>=0.18.0
Requires-Dist: twine>=4.0.0
Requires-Dist: build>=1.0.0
Requires-Dist: python-dotenv>=1.0.0
Provides-Extra: dev
Requires-Dist: pytest>=7.0; extra == "dev"
Requires-Dist: pytest-cov>=4.0; extra == "dev"
Requires-Dist: ruff>=0.6.0; extra == "dev"
Requires-Dist: mypy>=1.0; extra == "dev"
Requires-Dist: pre-commit>=3.0; extra == "dev"
Dynamic: license-file
